nexusmeo.cp36-win_amd64.pyd
nexusmeo-0.1.5.dist-info/METADATA
nexusmeo-0.1.5.dist-info/RECORD
nexusmeo-0.1.5.dist-info/WHEEL
nexusmeo-0.1.5.dist-info/top_level.txt
