Metadata-Version: 2.1
Name: nexusmeo
Version: 0.1.5
Summary: nexusmeo
Home-page: UNKNOWN
Author: Danian Hu
Author-email: hudanian@hotmail.com
License: UNKNOWN
Platform: UNKNOWN
